tabfix/__init__.py
tabfix/__main__.py
tabfix/api.py
tabfix/autoformat.py
tabfix/config.py
tabfix/core.py
tabfix/installer.py
tabfix_tool-1.2.6.1.dist-info/licenses/LICENSE
tabfix_tool-1.2.6.1.dist-info/METADATA
tabfix_tool-1.2.6.1.dist-info/WHEEL
tabfix_tool-1.2.6.1.dist-info/entry_points.txt
tabfix_tool-1.2.6.1.dist-info/top_level.txt
tabfix_tool-1.2.6.1.dist-info/RECORD
