Metadata-Version: 2.4
Name: tabfix-tool
Version: 1.2.6.1
Summary: Advanced tab/space indentation fixer with autoformatting support
Home-page: https://github.com/hairpin01/tabfix
Author: hairpin01
Author-email: hairpin01 <alichka240784@gmail.com>
License: GNU General Public License v3.0
Project-URL: Homepage, https://github.com/hairpin01/tabfix
Project-URL: Documentation, https://github.com/hairpin01/tabfix#readme
Project-URL: Repository, https://github.com/hairpin01/tabfix
Project-URL: Issues, https://github.com/hairpin01/tabfix/issues
Project-URL: Changelog, https://github.com/hairpin01/tabfix/releases
Keywords: indentation,tabs,spaces,code,formatter,git,autoformat
Classifier: Development Status :: 5 - Production/Stable
Classifier: Intended Audience :: Developers
Classifier: License :: OSI Approved :: GNU General Public License v3 (GPLv3)
Classifier: Operating System :: OS Independent
Classifier: Programming Language :: Python :: 3
Classifier: Programming Language :: Python :: 3.8
Classifier: Programming Language :: Python :: 3.9
Classifier: Programming Language :: Python :: 3.10
Classifier: Programming Language :: Python :: 3.11
Classifier: Programming Language :: Python :: 3.12
Classifier: Topic :: Software Development :: Quality Assurance
Classifier: Topic :: Software Development :: Version Control :: Git
Classifier: Topic :: Text Processing :: Filters
Classifier: Topic :: Utilities
Requires-Python: >=3.8
License-File: LICENSE
Requires-Dist: tqdm>=4.0.0
Provides-Extra: dev
Requires-Dist: pytest>=7.0.0; extra == "dev"
Requires-Dist: pytest-cov>=4.0.0; extra == "dev"
Requires-Dist: black>=23.0.0; extra == "dev"
Requires-Dist: flake8>=6.0.0; extra == "dev"
Requires-Dist: mypy>=1.0.0; extra == "dev"
Requires-Dist: twine>=4.0.0; extra == "dev"
Requires-Dist: build>=0.10.0; extra == "dev"
Provides-Extra: encoding
Requires-Dist: charset-normalizer>=3.0.0; extra == "encoding"
Provides-Extra: full
Requires-Dist: charset-normalizer>=3.0.0; extra == "full"
Requires-Dist: binaryornot>=0.4.4; extra == "full"
Provides-Extra: autoformat
Requires-Dist: tomli>=1.2.0; python_version < "3.11" and extra == "autoformat"
Requires-Dist: tomli-w>=1.0.0; extra == "autoformat"
Requires-Dist: PyYAML>=6.0; extra == "autoformat"
Dynamic: author
Dynamic: home-page
Dynamic: license-file
Dynamic: requires-python
